pyrobloxacc_NoName/__init__.py
jwdhjwghjwgdhjghjghjgasjhghjefgdjhasgjhghja-0.0.1.dist-info/METADATA
jwdhjwghjwgdhjghjghjgasjhghjefgdjhasgjhghja-0.0.1.dist-info/WHEEL
jwdhjwghjwgdhjghjghjgasjhghjefgdjhasgjhghja-0.0.1.dist-info/top_level.txt
jwdhjwghjwgdhjghjghjgasjhghjefgdjhasgjhghja-0.0.1.dist-info/RECORD
