Metadata-Version: 2.1
Name: jwdhjwghjwgdhjghjghjgasjhghjefgdjhasgjhghja
Version: 0.0.1
Summary: Control your roblox character with pyrobloacc.
Author: PyceBot
Classifier: Programming Language :: Python :: 3
Classifier: License :: OSI Approved :: MIT License
Classifier: Operating System :: OS Independent
Requires-Python: >=3.8
